{
  "project_info": {
    "project_number": "52810814573",
    "project_id": "nexus-e96e0",
    "storage_bucket": "nexus-e96e0.firebasestorage.app"
  },
  "client": [
    {
      "client_info": {
        "mobilesdk_app_id": "1:52810814573:android:609701709e4ee27c6b9b64",
        "android_client_info": {
          "package_name": "com.madiyar.nexus"
        }
      },
      "oauth_client": [],
      "api_key": [
        {
          "current_key": "AIzaSyAjumgPG1LUhGx4hI_f9x8hYHlK5JVNHcs"
        }
      ],
      "services": {
        "appinvite_service": {
          "other_platform_oauth_client": []
        }
      }
    }
  ],
  "configuration_version": "1"
}